{"E1": "Notification time out: <*>", "E2": "Received connection request /<*>:<*>", "E3": "Send worker leaving thread", "E4": "Interrupted while waiting for message on queue", "E5": "Connection broken for id <*>, my id =<*>, error =<*>", "E6": "Interrupting SendWorker", "E7": "Closed socket connection for client /<*>:<*> which had sessionid <*>", "E8": "caught end of stream exception", "E9": "Client attempting to renew session <*> at /<*>:<*>", "E10": "Client attempting to establish new session at /<*>:<*>", "E11": "Established session <*> with negotiated timeout <*> for client /<*>:<*>", "E12": "Accepted socket connection from /<*>:<*>", "E13": "Unexpected Exception:", "E14": "Connection request from old client /<*>:<*>; will be dropped if server is in r-o mode", "E15": "Server environment:<*>=<*>", "E16": "Cannot open channel to <*> at election address /<*>:<*>", "E17": "Processed session termination for sessionid: <*>", "E18": "Expiring session <*>, timeout of <*> exceeded", "E19": "******* GOODBYE /<*>:<*> ********", "E20": "LOOKING", "E21": "My election bind port: <*>/<*>:<*>", "E22": "Have smaller server identifier, so dropping the connection: (<*>, <*>)", "E23": "FOLLOWING", "E24": "New election. My id =<*> <*>, proposed zxid=<*>", "E25": "Server environment:<*>=<*>-master-<*>", "E26": "FOLLOWING - LEADER ELECTION TOOK - <*>", "E27": "Notification: <*>", "E28": "<*> set to <*>", "E29": "Server environment:<*>=<*> Corporation", "E30": "Revalidating client: <*>", "E31": "Closed socket connection for client /<*>:<*> (no session established for client)", "E32": "Exception causing close of session <*> due to <*>: ZooKeeperServer not running", "E33": "tickTime set to <*>", "E34": "Unexpected exception causing shutdown while sock still open", "E35": "Got user-level KeeperException when processing sessionid:<*>", "E36": "Starting quorum peer", "E37": "Snapshotting: <*> to <*>", "E38": "Follower sid: <*> : info : <*>$QuorumServer@<*>", "E39": "maxSessionTimeout set to -<*>", "E40": "Have quorum of supporters; starting up and setting last processed zxid: <*>", "E41": "shutdown of request processor complete", "E42": "First is <*>", "E43": "Reading snapshot <*>", "E44": "Sending DIFF", "E45": "Getting a snapshot from leader", "E46": "minSessionTimeout set to -<*>"}